simple_calculator_walid_fawaz/__init__.py
simple_calculator_walid_fawaz/calculator.py
simple_calculator_walid_fawaz-0.1.0.dist-info/METADATA
simple_calculator_walid_fawaz-0.1.0.dist-info/WHEEL
simple_calculator_walid_fawaz-0.1.0.dist-info/top_level.txt
simple_calculator_walid_fawaz-0.1.0.dist-info/RECORD
