Metadata-Version: 2.4
Name: simple-calculator-walid-fawaz
Version: 0.1.0
Summary: A simple calculator package for basic math operations
Home-page: https://github.com/walidfawaz/simple-calculator
Author: Walid Fawaz
Author-email: walid.fawaz@example.com
Classifier: Programming Language :: Python :: 3
Classifier: License :: OSI Approved :: MIT License
Classifier: Operating System :: OS Independent
Requires-Python: >=3.6
Dynamic: author
Dynamic: author-email
Dynamic: classifier
Dynamic: description
Dynamic: description-content-type
Dynamic: home-page
Dynamic: requires-python
Dynamic: summary
